<annotation>
	<folder>JPEGImages</folder>
	<filename>Potato_Early_blight_masked_27559.jpg</filename>
	<path>C:\Users\sanjeevk\LeafDetectData\LEAF2019\JPEGImages\Potato_Early_blight_masked_27559.jpg</path>
	<source>
		<database>Unknown</database>
	</source>
	<size>
		<width>256</width>
		<height>256</height>
		<depth>3</depth>
	</size>
	<segmented>0</segmented>
	<object>
		<name>Infected_Potato_Early_blight</name>
		<pose>Unspecified</pose>
		<truncated>1</truncated>
		<difficult>0</difficult>
		<bndbox>
			<xmin>9</xmin>
			<ymin>1</ymin>
			<xmax>247</xmax>
			<ymax>246</ymax>
		</bndbox>
	</object>
</annotation>
