<annotation>
	<folder>JPEGImages</folder>
	<filename>Tomato_Leaf_Mold_45254.jpg</filename>
	<path>C:\Users\sanjeevk\LeafDetectData\LEAF2019\JPEGImages\Tomato_Leaf_Mold_45254.jpg</path>
	<source>
		<database>Unknown</database>
	</source>
	<size>
		<width>256</width>
		<height>256</height>
		<depth>3</depth>
	</size>
	<segmented>0</segmented>
	<object>
		<name>Infected_Tomato_Leaf_Mold</name>
		<pose>Unspecified</pose>
		<truncated>0</truncated>
		<difficult>0</difficult>
		<bndbox>
			<xmin>26</xmin>
			<ymin>30</ymin>
			<xmax>242</xmax>
			<ymax>227</ymax>
		</bndbox>
	</object>
	<object>
		<name>Tomato_Leaf_Mold</name>
		<pose>Unspecified</pose>
		<truncated>0</truncated>
		<difficult>0</difficult>
		<bndbox>
			<xmin>45</xmin>
			<ymin>137</ymin>
			<xmax>97</xmax>
			<ymax>177</ymax>
		</bndbox>
	</object>
</annotation>
